guillaumechervet_picsou/__init__.py
guillaumechervet_picsou/picsou.py
guillaumechervet_picsou-0.1.0.dist-info/METADATA
guillaumechervet_picsou-0.1.0.dist-info/WHEEL
guillaumechervet_picsou-0.1.0.dist-info/RECORD
