Metadata-Version: 2.1
Name: guillaumechervet-picsou
Version: 0.1.0
Summary: 
Author: Guillaume Chervet
Author-email: guillaume.chervet@gmail.com
Requires-Python: >=3.10,<4.0
Classifier: Programming Language :: Python :: 3
Classifier: Programming Language :: Python :: 3.10
Classifier: Programming Language :: Python :: 3.11
Requires-Dist: coverage (>=7.4.1,<8.0.0)
Requires-Dist: pillow (==10.2.0)
